paramiko_jump/__init__.py
paramiko_jump/client.py
paramiko_jump/handler.py
paramiko_jump/py.typed
paramiko_jump-0.1.3.dist-info/LICENSE
paramiko_jump-0.1.3.dist-info/METADATA
paramiko_jump-0.1.3.dist-info/WHEEL
paramiko_jump-0.1.3.dist-info/top_level.txt
paramiko_jump-0.1.3.dist-info/RECORD
