Metadata-Version: 2.1
Name: paramiko-jump
Version: 0.1.3
Summary: Paramiko extension providing support for 2FA / MFA, SSH Proxying
Author-email: Andrew Schenck <aschenck@gmail.com>, Tyler Bruno <tybruno117@gmail.com>
Maintainer-email: Andrew Schenck <aschenck@gmail.com>
Project-URL: repository, https://github.com/andrewschenck/paramiko-jump
Requires-Python: >=3.6
License-File: LICENSE
Requires-Dist: paramiko >=3.4.0
